[
    { "name": "Google Takeout", "formats": ["ZIP", "JSON", "CSV", "MBOX", "HTML", "TXT"], "deletionRequired": false, "processTime": "Minutes to Days", "exportLink": "https://takeout.google.com/", "notes": "Comprehensive tool for most Google services (Gmail, Drive, Photos, etc.).", "lastVerifiedDate": "2025-06-20" },
    { "name": "Facebook", "formats": ["HTML", "JSON"], "deletionRequired": false, "processTime": "Minutes to Hours", "exportLink": "https://www.facebook.com/dyi/", "notes": "'Download Your Information' tool for posts, photos, messages, and more.", "lastVerifiedDate": "2025-06-20" },
    { "name": "Twitter (X)", "formats": ["JSON", "CSV", "HTML"], "deletionRequired": false, "processTime": "Minutes to Hours", "exportLink": "https://twitter.com/settings/your_twitter_data", "notes": "Archive includes tweets, DMs, media, and follower lists.", "lastVerifiedDate": "2025-06-20" },
    { "name": "Instagram", "formats": ["JSON", "HTML"], "deletionRequired": false, "processTime": "Hours to 2 Days", "exportLink": "https://www.instagram.com/download/request/", "notes": "Request your data via settings. Includes photos, videos, and comments.", "lastVerifiedDate": "2025-06-20" },
    { "name": "LinkedIn", "formats": ["CSV", "JSON", "XML"], "deletionRequired": false, "processTime": "Minutes to Hours", "exportLink": "https://www.linkedin.com/psettings/member-data", "notes": "Offers multiple archives: connections, messages, job applications, etc.", "lastVerifiedDate": "2025-06-20" },
    { "name": "GitHub", "formats": ["ZIP", "JSON"], "deletionRequired": false, "processTime": "Minutes", "exportLink": "https://github.com/settings/admin", "notes": "Account data download is available. For repositories, use standard Git clone.", "lastVerifiedDate": "2025-06-20" },
    { "name": "Spotify", "formats": ["JSON"], "deletionRequired": false, "processTime": "Days to Weeks", "exportLink": "https://www.spotify.com/account/privacy/", "notes": "Includes personal data and streaming history. Can take up to 30 days.", "lastVerifiedDate": "2025-06-20" },
    { "name": "Reddit", "formats": ["JSON"], "deletionRequired": false, "processTime": "Hours to Days", "exportLink": "https://www.reddit.com/settings/data", "notes": "Includes posts, comments, messages, and saved content.", "lastVerifiedDate": "2025-06-20" },
    { "name": "Netflix", "formats": ["CSV"], "deletionRequired": false, "processTime": "Minutes", "exportLink": "https://www.netflix.com/account/privacy", "notes": "Download viewing history, interaction data, and payment information.", "lastVerifiedDate": "2025-06-20" },
    { "name": "Twitch", "formats": ["JSON"], "deletionRequired": false, "processTime": "Days", "exportLink": "https://www.twitch.tv/settings/privacy", "notes": "Request your data from privacy settings. May take several days for large archives.", "lastVerifiedDate": "2025-06-20" },
    { "name": "Discord", "formats": ["JSON"], "deletionRequired": false, "processTime": "Hours to Days", "exportLink": "https://discord.com/settings/privacy", "notes": "Request all your data via User Settings > Privacy & Safety.", "lastVerifiedDate": "2025-06-20" },
    { "name": "Microsoft Account", "formats": ["JSON", "CSV", "HTML", "ZIP"], "deletionRequired": false, "processTime": "Minutes to Hours", "exportLink": "https://account.microsoft.com/privacy/download-data", "notes": "Download data across Outlook, Xbox, search history, Edge, etc.", "lastVerifiedDate": "2025-06-20" },
    { "name": "Amazon", "formats": ["ZIP", "CSV", "JSON"], "deletionRequired": false, "processTime": "Hours to Days", "exportLink": "https://www.amazon.com/gp/privacycentral/data-requests", "notes": "Request data like orders, payment history, and interactions.", "lastVerifiedDate": "2025-06-20" },
    { "name": "Apple (Privacy Portal)", "formats": ["CSV", "JSON", "PDF", "ZIP"], "deletionRequired": false, "processTime": "Days to Weeks", "exportLink": "https://privacy.apple.com/", "notes": "Comprehensive request for data across iCloud, Apple ID, App Store, etc.", "lastVerifiedDate": "2025-06-20" },
    { "name": "Adobe", "formats": ["JSON", "CSV"], "deletionRequired": false, "processTime": "Hours to Days", "exportLink": "https://account.adobe.com/privacy", "notes": "Request a copy of personal data, product usage data, and content.", "lastVerifiedDate": "2025-06-20" },
    { "name": "Zoom", "formats": ["CSV", "JSON"], "deletionRequired": false, "processTime": "Minutes to Hours", "exportLink": "https://zoom.us/profile/setting?setting_page=data_management", "notes": "Request a copy of your meeting logs, chat history, and account activity.", "lastVerifiedDate": "2025-06-20" },
    { "name": "Slack", "formats": ["JSON", "CSV"], "deletionRequired": false, "processTime": "Hours to Days", "exportLink": "https://slack.com/account/settings#privacy", "notes": "Workspace owners can export all data. Individuals can export DM history.", "lastVerifiedDate": "2025-06-20" },
    { "name": "TikTok", "formats": ["TXT", "JSON"], "deletionRequired": false, "processTime": "Hours to Days", "exportLink": "https://www.tiktok.com/setting/download-your-data", "notes": "Download includes profile info, activity, and app settings.", "lastVerifiedDate": "2025-06-20" },
    { "name": "Pinterest", "formats": ["JSON"], "deletionRequired": false, "processTime": "Hours to 2 Days", "exportLink": "https://www.pinterest.com/settings/privacy-and-data/", "notes": "Request your data, which includes your pins, boards, and account history.", "lastVerifiedDate": "2025-06-20" },
    { "name": "Dropbox", "formats": ["ZIP"], "deletionRequired": false, "processTime": "Minutes", "exportLink": "https://www.dropbox.com/account/general", "notes": "Download all files easily. Account information can be requested separately.", "lastVerifiedDate": "2025-06-20" },
    { "name": "Steam", "formats": ["JSON", "HTML"], "deletionRequired": false, "processTime": "Days to Weeks", "exportLink": "https://help.steampowered.com/en/accountdata", "notes": "Request data from Steam Support. Can take up to 30 days.", "lastVerifiedDate": "2025-06-20" },
    { "name": "PayPal", "formats": ["PDF", "CSV"], "deletionRequired": false, "processTime": "Minutes to Hours", "exportLink": "https://www.paypal.com/myaccount/privacy/data", "notes": "Request reports of your transaction history and other account data.", "lastVerifiedDate": "2025-06-20" },
    { "name": "Notion", "formats": ["Markdown", "CSV", "HTML"], "deletionRequired": false, "processTime": "Minutes", "exportLink": "https://www.notion.so/my-account", "notes": "Workspace owners can export the entire workspace. Also per-page exports.", "lastVerifiedDate": "2025-06-20" },
    { "name": "Trello", "formats": ["JSON", "CSV"], "deletionRequired": false, "processTime": "Minutes", "exportLink": "https://trello.com/my/profile", "notes": "Board data can be exported in JSON format from the board menu.", "lastVerifiedDate": "2025-06-20" },
    { "name": "Telegram", "formats": ["JSON", "HTML"], "deletionRequired": false, "processTime": "Hours", "exportLink": "https://desktop.telegram.org/", "notes": "Data export is only available through the Telegram Desktop application.", "lastVerifiedDate": "2025-06-20" },
    { "name": "WhatsApp", "formats": ["TXT", "ZIP"], "deletionRequired": false, "processTime": "Minutes to Hours", "exportLink": "https://www.whatsapp.com/settings/request-account-info", "notes": "Request account info report in app settings. Does not include messages, which can be exported per-chat.", "lastVerifiedDate": "2025-06-20" },
    { "name": "Figma", "formats": ["FIG", "SVG", "PNG", "JPG"], "deletionRequired": false, "processTime": "Minutes", "exportLink": "https://www.figma.com/files/", "notes": "Export entire design files (.fig) or export individual frames/assets to various image formats directly from the editor.", "lastVerifiedDate": "2025-06-20" },
    { "name": "Canva", "formats": ["PDF", "PNG", "JPG", "MP4"], "deletionRequired": false, "processTime": "Minutes", "exportLink": "https://www.canva.com/", "notes": "Designs are exported individually from the editor. No single account data dump is available, but all creations can be downloaded.", "lastVerifiedDate": "2025-06-20" },
    { "name": "Vercel", "formats": ["JSON", "Log"], "deletionRequired": false, "processTime": "Minutes", "exportLink": "https://vercel.com/account/data", "notes": "Export personal account data and team data. Source code is managed via Git.", "lastVerifiedDate": "2025-06-20" },
    { "name": "Netlify", "formats": ["JSON", "ZIP"], "deletionRequired": false, "processTime": "Minutes", "exportLink": "https://app.netlify.com/user/settings", "notes": "Request personal data from user settings. Site deploys can be downloaded as ZIP files.", "lastVerifiedDate": "2025-06-20" },
    { "name": "DigitalOcean", "formats": ["JSON"], "deletionRequired": false, "processTime": "Minutes", "exportLink": "https://cloud.digitalocean.com/account/profile", "notes": "Most data is managed via API (droplets, volumes). Personal account information can be requested via support ticket.", "lastVerifiedDate": "2025-06-20" },
    { "name": "Etsy", "formats": ["CSV"], "deletionRequired": false, "processTime": "Minutes", "exportLink": "https://www.etsy.com/your/account/privacy", "notes": "Download your data, including order history and favorites, from your account's Privacy settings.", "lastVerifiedDate": "2025-06-20" },
    { "name": "Bandcamp", "formats": ["MP3", "FLAC", "WAV"], "deletionRequired": false, "processTime": "Minutes", "exportLink": "https://bandcamp.com/download_dialog", "notes": "All purchases can be re-downloaded at any time from your collection page in various high-quality audio formats.", "lastVerifiedDate": "2025-06-20" }
]
